spiro/__init__.py
spiro-0.1.2.dist-info/DESCRIPTION.rst
spiro-0.1.2.dist-info/METADATA
spiro-0.1.2.dist-info/RECORD
spiro-0.1.2.dist-info/WHEEL
spiro-0.1.2.dist-info/metadata.json
spiro-0.1.2.dist-info/top_level.txt
