Metadata-Version: 2.0
Name: spiro
Version: 0.1.2
Summary: Module to draw spirographs with turtle graphics
Home-page: https://github.com/daviddekoning/spiro
Author: David de Koning
Author-email: david.dekoning+spiro@gmail.com
License: UNKNOWN
Keywords: turtle spirograph education graphics
Platform: UNKNOWN
Classifier: Development Status :: 3 - Alpha
Classifier: Intended Audience :: Education
Classifier: Topic :: Artistic Software
Classifier: Topic :: Education
Classifier: License :: OSI Approved :: MIT License
Classifier: Programming Language :: Python :: 3.6
Requires-Python: >=3.6
